mangust228/__init__.py
mangust228/parsed/__init__.py
mangust228/parsed/_logger.py
mangust228/parsed/async_manager.py
mangust228/parsed/sync_manager.py
mangust228/proxy/__init__.py
mangust228/proxy/_base.py
mangust228/proxy/_config.py
mangust228/proxy/_exceptions.py
mangust228/proxy/_logger.py
mangust228/proxy/_schemas.py
mangust228/proxy/async_manager.py
mangust228/proxy/sync_manager.py
mangust228/repo/__init__.py
mangust228/repo/_logger.py
mangust228/repo/base_async_repo.py
mangust228/repo/base_sync_repo.py
mangust228/repo/exceptions.py
mangust228/repo/factory_async_repo.py
mangust228/repo/factory_sync_repo.py
mangust228/saver/__init__.py
mangust228/saver/_base.py
mangust228/saver/_exceptions.py
mangust228/saver/_logger.py
mangust228/saver/async_saver.py
mangust228/saver/sync_saver.py
mangust228/ua/__init__.py
mangust228/ua/_browsers.py
mangust228/ua/_descriptor.py
mangust228/ua/_engines.py
mangust228/ua/_exceptions.py
mangust228/ua/_oses.py
mangust228/ua/ua_random.py
mangust228-0.8.25.dist-info/METADATA
mangust228-0.8.25.dist-info/WHEEL
mangust228-0.8.25.dist-info/top_level.txt
mangust228-0.8.25.dist-info/RECORD
