Metadata-Version: 2.1
Name: mangust228
Version: 0.8.25
Summary: Lazy utils each I use sometimes
Home-page: https://github.com/mangustik228/proxy_manager
Author: mangust228
Author-email: bacek.mangust@gmail.com
Classifier: Programming Language :: Python :: 3
Classifier: License :: OSI Approved :: MIT License
Classifier: Operating System :: OS Independent
Requires-Python: >=3.9
Provides-Extra: all
Requires-Dist: sqlalchemy ; extra == 'all'
Requires-Dist: aiofiles ; extra == 'all'
Requires-Dist: aiocsv ; extra == 'all'
Requires-Dist: httpx ; extra == 'all'
Requires-Dist: nanoid ; extra == 'all'
Provides-Extra: parsed
Requires-Dist: aiofiles ; extra == 'parsed'
Requires-Dist: aiocsv ; extra == 'parsed'
Provides-Extra: proxy
Requires-Dist: httpx ; extra == 'proxy'
Provides-Extra: repo
Requires-Dist: sqlalchemy ; extra == 'repo'
Provides-Extra: saver
Requires-Dist: aiofiles ; extra == 'saver'
Requires-Dist: nanoid ; extra == 'saver'
Provides-Extra: ua
